interactflow/__init__.py
interactflow/main.py
interactflow/player.py
interactflow/recorder.py
interactflow/version.py
interactflow-1.0.3.dist-info/LICENSE
interactflow-1.0.3.dist-info/METADATA
interactflow-1.0.3.dist-info/WHEEL
interactflow-1.0.3.dist-info/entry_points.txt
interactflow-1.0.3.dist-info/top_level.txt
interactflow-1.0.3.dist-info/RECORD
