Metadata-Version: 2.1
Name: interactflow
Version: 1.0.3
Summary: A powerful tool for recording and replaying user interactions
Home-page: https://github.com/yashChouriya/interactflow
Author: InteractFlow Team
Author-email: yashchouriya131+github@gmail.com
Classifier: Development Status :: 4 - Beta
Classifier: Intended Audience :: Developers
Classifier: Topic :: Software Development :: Testing
Classifier: Topic :: Software Development :: Libraries :: Python Modules
Classifier: Topic :: System :: Monitoring
Classifier: Topic :: Utilities
Classifier: License :: OSI Approved :: MIT License
Classifier: Programming Language :: Python :: 3
Classifier: Programming Language :: Python :: 3.6
Classifier: Programming Language :: Python :: 3.7
Classifier: Programming Language :: Python :: 3.8
Classifier: Programming Language :: Python :: 3.9
Classifier: Operating System :: OS Independent
Requires-Python: >=3.6
License-File: LICENSE
Requires-Dist: pynput>=1.7.6
Requires-Dist: python-xlib>=0.33
